file_utils_operations-0.2.0.dist-info/METADATA
file_utils_operations-0.2.0.dist-info/WHEEL
file_utils_operations-0.2.0.dist-info/licenses/LICENSE
file_utils_operations_lib/__init__.py
file_utils_operations_lib/file_utils_operations_lib.cpython-310-x86_64-linux-gnu.so
file_utils_operations-0.2.0.dist-info/RECORD
